MANIFEST.in
README.rst
requirements.txt
setup.cfg
setup.py
extinctions/__init__.py
extinctions/extinction.py
extinctions/main.py
extinctions/reddening.py
extinctions/utils.py
extinctions/version.py
extinctions.egg-info/PKG-INFO
extinctions.egg-info/SOURCES.txt
extinctions.egg-info/dependency_links.txt
extinctions.egg-info/requires.txt
extinctions.egg-info/top_level.txt
extinctions/data/maps.yaml
extinctions/extern/__init__.py
extinctions/extern/argonaut.py
extinctions/extern/others.py
extinctions/extern/sncosmo.py
extinctions/extern/snfactory.py
scripts/extinction_plots.py
scripts/get_maps.py