Metadata-Version: 1.1
Name: extinctions
Version: 0.1.9
Summary: Extinction laws, maps and corrections
Home-page: https://github.com/nicolaschotard/extinctions
Author: Nicolas Chotard
Author-email: nchotard@in2p3.fr
License: MIT
Platform: UNKNOWN
Classifier: Development Status :: 3 - Alpha
Classifier: Intended Audience :: Science/Research
Classifier: Topic :: Software Development :: Build Tools
Classifier: License :: OSI Approved :: MIT License
Classifier: Programming Language :: Python :: 2
Classifier: Topic :: Scientific/Engineering :: Astronomy
